mkbc/__init__.py
mkbc/__main__.py
mkbc/formulas.py
mkbc/images.py
mkbc/macros.py
mkbc-2.4.0.dist-info/licenses/LICENCE
usr/share/mkbc/latex/main.tex
mkbc-2.4.0.dist-info/METADATA
mkbc-2.4.0.dist-info/WHEEL
mkbc-2.4.0.dist-info/entry_points.txt
mkbc-2.4.0.dist-info/top_level.txt
mkbc-2.4.0.dist-info/RECORD
