Metadata-Version: 2.4
Name: mkbc
Version: 2.4.0
Summary: Make ebook collection
Home-page: https://gitlab.com/pacholik1/MKBC
Author: Vojtěch Pachol
Author-email: pacholick@gmail.com
License: LGPL-3.0
Keywords: python,ebook
Classifier: Development Status :: 5 - Production/Stable
Classifier: Programming Language :: Python :: 3
License-File: LICENCE
Requires-Dist: httplib2
Requires-Dist: beautifulsoup4
Requires-Dist: cairosvg
Requires-Dist: Pillow
Requires-Dist: EbookLib
Requires-Dist: langdetect
Requires-Dist: qrcode
Dynamic: author
Dynamic: author-email
Dynamic: classifier
Dynamic: description
Dynamic: home-page
Dynamic: keywords
Dynamic: license
Dynamic: license-file
Dynamic: requires-dist
Dynamic: summary
